studentid_2401138/__init__.py
studentid_2401138/main.py
studentid_2401138-0.1.1.dist-info/licenses/LICENSE.txt
studentid_2401138-0.1.1.dist-info/METADATA
studentid_2401138-0.1.1.dist-info/WHEEL
studentid_2401138-0.1.1.dist-info/top_level.txt
studentid_2401138-0.1.1.dist-info/RECORD
